[
    {
        "name": "keypad",
        "type": "keypad",
        "pin": "usb",
        "pi": "ret-top",
        "state": "2915"
    },
    {
        "name": "astronomy-door-lock",
        "type": "maglock",
        "pin": 20,
        "pi": "mlv-astronomy",
        "state": "Unlocked",
        "connection_type": "NO"
    },
    {
        "name": "herbalist-door-lock",
        "type": "maglock",
        "pin": 23,
        "pi": "mlv-herbalist",
        "state": "Unlocked",
        "connection_type": "NO"
    },
    {
        "name": "moon-puzzle",
        "type": "Sensor",
        "pin": 17,
        "pi": "mlv-astronomy",
        "state": "Not Triggered",
        "connection_type": "NO"
    },
    {
        "name": "light_count",
        "type": "Sensor",
        "pin": 17,
        "pi": "mlv-corridors",
        "state": "0",
        "connection_type": "NO"
    },
    {
        "name": "knocker",
        "type": "Sensor",
        "pin": 0,
        "pi": "mlv-tavern",
        "state": "unsolved",
        "connection_type": "NO"
    }
    
]